caravan/swf.py
caravan/__init__.py
caravan/commands/decider.py
caravan/commands/terminate.py
caravan/commands/domain_list.py
caravan/commands/signal.py
caravan/commands/base.py
caravan/commands/start.py
caravan/commands/domain_register.py
caravan/commands/__init__.py
caravan/commands/list.py
caravan/testing/__init__.py
caravan/models/decision.py
caravan/models/workflow.py
caravan/models/__init__.py
caravan/workers/decider.py
caravan/workers/__init__.py
caravan/examples/demo.py
caravan/examples/__init__.py
caravan/tests/fixtures.py
caravan/tests/test_swf.py
caravan/tests/__init__.py
caravan/tests/util.py
caravan/tests/commands/test_base.py
caravan/tests/commands/test_decider.py
caravan/tests/commands/test_domain_list.py
caravan/tests/commands/test_terminate.py
caravan/tests/commands/test_signal.py
caravan/tests/commands/test_domain_register.py
caravan/tests/commands/test_start.py
caravan/tests/commands/test_list.py
caravan/tests/commands/__init__.py
caravan/tests/models/test_decision.py
caravan/tests/models/__init__.py
caravan/tests/examples/test_demo.py
caravan/tests/examples/__init__.py
caravan-0.2.2.dist-info/RECORD
caravan-0.2.2.dist-info/top_level.txt
caravan-0.2.2.dist-info/METADATA
caravan-0.2.2.dist-info/WHEEL
caravan-0.2.2.dist-info/entry_points.txt
caravan-0.2.2.dist-info/DESCRIPTION.rst
caravan-0.2.2.dist-info/metadata.json
