Metadata-Version: 2.0
Name: caravan
Version: 0.2.2
Summary: Light python framework for AWS SWF
Home-page: https://github.com/pior/caravan
Author: Pior Bastida
Author-email: pior@pbastida.net
License: MIT
Keywords: AWS SWF workflow distributed background task
Platform: UNKNOWN
Classifier: Development Status :: 3 - Alpha
Classifier: Intended Audience :: Developers
Classifier: License :: OSI Approved :: MIT License
Classifier: Operating System :: OS Independent
Classifier: Topic :: Internet
Classifier: Programming Language :: Python :: 2.7
Classifier: Programming Language :: Python :: 3.3
Classifier: Programming Language :: Python :: 3.4
Classifier: Programming Language :: Python :: 3.5
Classifier: Programming Language :: Python :: Implementation :: PyPy
Requires-Dist: boto3
Requires-Dist: arrow
Requires-Dist: six
Requires-Dist: tabulate
Requires-Dist: inflection
Provides-Extra: dev
Requires-Dist: nose; extra == 'dev'
Requires-Dist: nosexcover; extra == 'dev'
Requires-Dist: coverage; extra == 'dev'
Requires-Dist: yanc (==0.2.4); extra == 'dev'
Requires-Dist: mock; extra == 'dev'
Requires-Dist: freezegun; extra == 'dev'
Requires-Dist: abduct; extra == 'dev'
Requires-Dist: httpretty (==0.8.10); extra == 'dev'
Requires-Dist: moto; extra == 'dev'
Requires-Dist: zest.releaser[recommended]; extra == 'dev'
Requires-Dist: pylama; extra == 'dev'
